ezgpt/__init__.py
ezgpt/ezgpt.py
ezgpt-2.4.3.dist-info/LICENSE
ezgpt-2.4.3.dist-info/METADATA
ezgpt-2.4.3.dist-info/WHEEL
ezgpt-2.4.3.dist-info/top_level.txt
ezgpt-2.4.3.dist-info/RECORD
