Metadata-Version: 2.1
Name: ezgpt
Version: 2.4.3
Summary: A simple GPT interface
Home-page: https://github.com/Ascyt/ezgpt
Author: Filip Schauer
Author-email: contact@ascyt.com
License: MIT
Classifier: Programming Language :: Python :: 3
Classifier: License :: OSI Approved :: MIT License
Requires-Python: >=3.11.2
License-File: LICENSE
Requires-Dist: openai >=1.0.0
Requires-Dist: colorama
